nn_generator/__init__.py
nn_generator-1.0.1.dist-info/DESCRIPTION.rst
nn_generator-1.0.1.dist-info/METADATA
nn_generator-1.0.1.dist-info/RECORD
nn_generator-1.0.1.dist-info/WHEEL
nn_generator-1.0.1.dist-info/metadata.json
nn_generator-1.0.1.dist-info/top_level.txt
